byteblower/test_cases/rfc_2544/.gitignore
byteblower/test_cases/rfc_2544/__init__.py
byteblower/test_cases/rfc_2544/__main__.py
byteblower/test_cases/rfc_2544/_endpoint_factory.py
byteblower/test_cases/rfc_2544/_port_factory.py
byteblower/test_cases/rfc_2544/_version.py
byteblower/test_cases/rfc_2544/cli.py
byteblower/test_cases/rfc_2544/definitions.py
byteblower/test_cases/rfc_2544/exceptions.py
byteblower/test_cases/rfc_2544/report_generator.py
byteblower/test_cases/rfc_2544/scouting_flow.py
byteblower/test_cases/rfc_2544/throughput.py
byteblower/test_cases/rfc_2544/templates/config_summary.html
byteblower/test_cases/rfc_2544/templates/frame_results.html
byteblower/test_cases/rfc_2544/templates/pass_fail.html
byteblower/test_cases/rfc_2544/templates/report.html
byteblower/test_cases/rfc_2544/templates/report_footer.html
byteblower/test_cases/rfc_2544/templates/report_head_style.html
byteblower/test_cases/rfc_2544/templates/report_header.html
byteblower/test_cases/rfc_2544/templates/report_main.html
byteblower/test_cases/rfc_2544/templates/results_summary.html
byteblower/test_cases/rfc_2544/templates/css/embedded-fonts.css
byteblower/test_cases/rfc_2544/templates/css/rfc2544.css
byteblower/test_cases/rfc_2544/templates/css/testframework.css
byteblower_test_cases_rfc_2544-1.0.2.dist-info/entry_points.txt
byteblower_test_cases_rfc_2544-1.0.2.dist-info/LICENSE
byteblower_test_cases_rfc_2544-1.0.2.dist-info/WHEEL
byteblower_test_cases_rfc_2544-1.0.2.dist-info/METADATA
byteblower_test_cases_rfc_2544-1.0.2.dist-info/RECORD
